[
    {
        "link": "https://www.ddo.com/news/ddo-myth-drannor-release-date",
        "title": "Magic of Myth Drannor Release Date Information",
        "full_summary": "We are getting ready to release Magic of Myth Drannor and we want to share an updated release date with you today. Magic of Myth Drannor will release on Wednesday, August 14th, 2024. We currently have a loot preview happening on Lamannia, and we're planning for another preview later this month. We look forward to sharing more of our next expansion with you in the coming weeks!",
        "short_summary": "We are getting ready to release Magic of Myth Drannor and we want to share an updated release date\u2026",
        "date": "Thu Jul 11 2024",
        "coupon": null
    },
    {
        "link": "https://www.ddo.com/news/ddo-sales-071124",
        "title": "Sales: July 11th - 18th!",
        "full_summary": "Get the latest sales here!",
        "short_summary": "Get the latest sales here!",
        "date": "Thu Jul 11 2024",
        "coupon": {
            "item": "Free Potion of Rage x5",
            "code": "WHATWOULDGROGDO",
            "exp": "July 18th"
        }
    },
    {
        "link": "https://www.ddo.com/news/ddo-bonus-071124",
        "title": "DDO Bonus Days!",
        "full_summary": "DDO Bonus Days bring you a +30% Crafting XP Boost, now through July 14th!",
        "short_summary": "DDO Bonus Days bring you a +30% Crafting XP Boost, now through July 14th!",
        "date": "Thu Jul 11 2024",
        "coupon": null
    },
    {
        "link": "https://www.ddo.com/news/ddo-discord-volunteers-moderators",
        "title": "We're Looking for Volunteer Moderators for an Official\u2026",
        "full_summary": "We are looking forward to opening our first official Dungeons & Dragons Online Discord, and we are looking for some members of the community to volunteer to help make it a reality!",
        "short_summary": "We are looking forward to opening our first official Dungeons & Dragons Online Discord, and we are\u2026",
        "date": "Wed Jul 10 2024",
        "coupon": null
    },
    {
        "link": "https://www.ddo.com/news/ddo-downtime-071024",
        "title": "Downtime Notice: Wednesday, July 10th 9:00 AM - 4:30 PM\u2026",
        "full_summary": "UPDATE: The game worlds have reopened. Thank you for your patience during today's downtime.\nThe DDO game worlds will be down for extended maintenance on Wednesday, July 10th from 9:00 AM - 4:30 PM Eastern (-4 GMT). Thank you for your patience, and we'll see you back in the game soon!",
        "short_summary": "UPDATE: The game worlds have reopened. Thank you for your patience during today's downtime.\u2026",
        "date": "Tue Jul 09 2024",
        "coupon": null
    },
    {
        "link": "https://www.ddo.com/news/ddo-sales-070324",
        "title": "Sales: July 3rd - 11th!",
        "full_summary": "Get the latest sales here!",
        "short_summary": "Get the latest sales here!",
        "date": "Wed Jul 03 2024",
        "coupon": {
            "item": "Free Medium Guild Renown Elixir",
            "code": "PRESTIGE",
            "exp": "July 11th"
        }
    },
    {
        "link": "https://www.ddo.com/news/ddo-bonus-070324",
        "title": "DDO Bonus Days!",
        "full_summary": "DDO Bonus Days bring you a +5% Reaper XP Boost, now through July 7th!",
        "short_summary": "DDO Bonus Days bring you a +5% Reaper XP Boost, now through July 7th!",
        "date": "Wed Jul 03 2024",
        "coupon": null
    },
    {
        "link": "https://www.ddo.com/news/ddo-sales-062724",
        "title": "Sales: June 27th - July 4th",
        "full_summary": "Get the latest sales here!",
        "short_summary": "Get the latest sales here!",
        "date": "Thu Jun 27 2024",
        "coupon": {
            "item": "Free Sun Flasks x25",
            "code": "HAVEABLAST",
            "exp": "July 4th"
        }
    },
    {
        "link": "https://www.ddo.com/news/ddo-bonus-062724",
        "title": "DDO Bonus Days!",
        "full_summary": "DDO Bonus Days bring you a +40% Challenge Rewards Boost, now through June 30th!",
        "short_summary": "DDO Bonus Days bring you a +40% Challenge Rewards Boost, now through June 30th!",
        "date": "Thu Jun 27 2024",
        "coupon": null
    },
    {
        "link": "https://www.ddo.com/news/ddo-year-of-the-dragon-june",
        "title": "Year of the Dragon - June!",
        "full_summary": "Read more about June's Year of the Dragon Gift, the Dragon Hatchling Creature Companion!",
        "short_summary": "Read more about June's Year of the Dragon Gift, the Dragon Hatchling Creature Companion!",
        "date": "Tue Jun 25 2024",
        "coupon": null
    },
    {
        "link": "https://www.ddo.com/news/ddo-sales-062024",
        "title": "Sales: June 20th - 27th",
        "full_summary": "Get the latest sales here!",
        "short_summary": "Get the latest sales here!",
        "date": "Thu Jun 20 2024",
        "coupon": {
            "item": "Free Secret Door Divining Rod",
            "code": "SEEKRETS",
            "exp": "June 27th"
        }
    },
    {
        "link": "https://www.ddo.com/news/ddo-bonus-062024",
        "title": "DDO Bonus Days!",
        "full_summary": "DDO Bonus Days bring you Double Daily Dice XP, now through June 23rd!",
        "short_summary": "DDO Bonus Days bring you Double Daily Dice XP, now through June 23rd!",
        "date": "Thu Jun 20 2024",
        "coupon": null
    }
]